MANIFEST.in
README.md
setup.cfg
setup.py
testhttpserver/__init__.py
testhttpserver/server.py
testhttpserver.egg-info/PKG-INFO
testhttpserver.egg-info/SOURCES.txt
testhttpserver.egg-info/dependency_links.txt
testhttpserver.egg-info/top_level.txt
testhttpserver.egg-info/zip-safe