Metadata-Version: 1.0
Name: testhttpserver
Version: 0.1.4
Summary: A HTTP server to use for testing
Home-page: https://github.com/philipcristiano/testhttpserver
Author: Philip Cristiano
Author-email: testhttpserver@philipcristiano.com
License: BSD
Keywords: testing
Platform: UNKNOWN
Classifier: Development Status :: 4 - Beta
Classifier: Intended Audience :: Developers
Classifier: License :: OSI Approved :: BSD License
Classifier: Programming Language :: Python
